historian/sql/__init__.py
historian/sql/basedb.py
historian/sql/historian.py
historian/sql/sqlutils.py
volttron_lib_sql_historian-2.0.0rc1.dist-info/LICENSE
volttron_lib_sql_historian-2.0.0rc1.dist-info/METADATA
volttron_lib_sql_historian-2.0.0rc1.dist-info/WHEEL
volttron_lib_sql_historian-2.0.0rc1.dist-info/RECORD
