Metadata-Version: 2.3
Name: volttron-lib-sql-historian
Version: 2.0.0rc1
Summary: A library for supporting sql based historians.
License: Apache-2.0
Author: VOLTTRON Team
Author-email: volttron@pnnl.gov
Requires-Python: >=3.10,<4.0
Classifier: License :: OSI Approved :: Apache Software License
Classifier: Programming Language :: Python :: 3
Classifier: Programming Language :: Python :: 3.10
Classifier: Programming Language :: Python :: 3.11
Classifier: Programming Language :: Python :: 3.12
Classifier: Programming Language :: Python :: 3.13
Requires-Dist: volttron-lib-base-historian (>=2.0.0rc0)
Project-URL: Homepage, https://github.com/eclipse-volttron/volttron-lib-sql-historian
Project-URL: Repository, https://github.com/eclipse-volttron/volttron-lib-sql-historian
